zyxel_nebula_client/__init__.py
zyxel_nebula_client/client.py
zyxel_nebula_client/consts.py
zyxel_nebula_client/models.py
zyxel_nebula_client-0.1.3.dist-info/LICENSE
zyxel_nebula_client-0.1.3.dist-info/METADATA
zyxel_nebula_client-0.1.3.dist-info/WHEEL
zyxel_nebula_client-0.1.3.dist-info/RECORD
