Metadata-Version: 2.1
Name: zyxel-nebula-client
Version: 0.1.3
Summary: Python Client for interacting with the Zyxel Nebula API
Home-page: https://github.com/cemizm/zyxel-nebula-client
License: MIT
Author: Cem Basoglu
Author-email: cem.basoglu@web.de
Requires-Python: >=3.12,<4.0
Classifier: License :: OSI Approved :: MIT License
Classifier: Programming Language :: Python :: 3
Classifier: Programming Language :: Python :: 3.12
Classifier: Programming Language :: Python :: 3.13
Requires-Dist: dacite (>=1.8.1,<2.0.0)
Requires-Dist: httpx (>=0.27.2,<0.28.0)
